CHANGES.txt
COPYRIGHT.txt
LICENSE.txt
README.txt
TODO.txt
ez_setup.py
setup.cfg
setup.py
test.ini
docs/Makefile
docs/conf.py
docs/index.rst
docs/.static/logo_hi.gif
docs/.static/repoze.css
repoze/__init__.py
repoze.annotea.egg-info/PKG-INFO
repoze.annotea.egg-info/SOURCES.txt
repoze.annotea.egg-info/dependency_links.txt
repoze.annotea.egg-info/entry_points.txt
repoze.annotea.egg-info/namespace_packages.txt
repoze.annotea.egg-info/not-zip-safe
repoze.annotea.egg-info/requires.txt
repoze.annotea.egg-info/top_level.txt
repoze/annotea/__init__.py
repoze/annotea/configure.zcml
repoze/annotea/interfaces.py
repoze/annotea/main.py
repoze/annotea/models.py
repoze/annotea/scripts/__init__.py
repoze/annotea/scripts/export_annotations.py
repoze/annotea/tests/__init__.py
repoze/annotea/tests/test_models.py
repoze/annotea/views/__init__.py
repoze/annotea/views/annotation.py
repoze/annotea/views/configure.zcml
repoze/annotea/views/service.py
repoze/annotea/views/utils.py
repoze/annotea/views/tests/__init__.py
repoze/annotea/views/tests/test_annotation.py
repoze/annotea/views/tests/test_service.py