Metadata-Version: 1.0
Name: repoze.annotea
Version: 0.1
Summary: Implement W3C Annotea server in repoze
Home-page: http://www.repoze.org
Author: Agendaless Consulting
Author-email: repoze-dev@lists.repoze.org
License: BSD-derived (http://www.repoze.org/LICENSE.txt)
Keywords: web wsgi zope annotation
Platform: UNKNOWN
Classifier: Development Status :: 3 - Alpha
Classifier: Intended Audience :: Developers
Classifier: Programming Language :: Python
Classifier: Topic :: Internet :: WWW/HTTP
Classifier: Topic :: Internet :: WWW/HTTP :: Dynamic Content
Classifier: Topic :: Internet :: WWW/HTTP :: WSGI
